EventPublisher/JsonParser.py
EventPublisher/Publisher.py
EventPublisher/SupportedEvents.py
EventPublisher/__init__.py
EventPublisher/EventHub/EventHubProducer.py
EventPublisher/EventHub/Response.py
EventPublisher/EventHub/SendEvents.py
EventPublisher/EventHub/__init__.py
EventPublisher/Settings/Configuration.py
EventPublisher/Settings/Settings.py
EventPublisher/Settings/SettingsDefaults.py
EventPublisher/Settings/__init__.py
EventHubPublisher-0.0.30.dist-info/METADATA
EventHubPublisher-0.0.30.dist-info/WHEEL
EventHubPublisher-0.0.30.dist-info/top_level.txt
EventHubPublisher-0.0.30.dist-info/RECORD
