Metadata-Version: 2.1
Name: EventHubPublisher
Version: 0.0.30
Summary: A small example package
Home-page: https://storis.com
Author: STORIS
Author-email: author@example.com
Project-URL: Bug Tracker, https://storis.com
Classifier: Programming Language :: Python :: 3
Classifier: License :: OSI Approved :: MIT License
Classifier: Operating System :: OS Independent
Requires-Python: >=3.6
Requires-Dist: setuptools (>=42)
Requires-Dist: wheel (>=0.37.1)
Requires-Dist: requests (>=2.27.1)
Requires-Dist: azure-eventhub (>=5.7.0)
